seclai/__init__.py
seclai/_generated/.gitignore
seclai/_generated/.gitkeep
seclai/_generated/README.md
seclai/_generated/__init__.py
seclai/_generated/api/__init__.py
seclai/_generated/api/agents/__init__.py
seclai/_generated/api/agents/delete_agent_run_api_agents_runs_run_id_delete.py
seclai/_generated/api/agents/get_agent_run_api_agents_runs_run_id_get.py
seclai/_generated/api/agents/list_agent_runs_api_agents_agent_id_runs_get.py
seclai/_generated/api/agents/run_agent_api_agents_agent_id_runs_post.py
seclai/_generated/api/agents/run_streaming_agent_api_agents_agent_id_runs_stream_post.py
seclai/_generated/api/contents/__init__.py
seclai/_generated/api/contents/delete_content_api_contents_source_connection_content_version_delete.py
seclai/_generated/api/contents/get_content_detail_api_contents_source_connection_content_version_get.py
seclai/_generated/api/contents/list_content_embeddings_api_contents_source_connection_content_version_embeddings_get.py
seclai/_generated/api/contents/upload_file_to_content_api_contents_source_connection_content_version_upload_post.py
seclai/_generated/api/sources/__init__.py
seclai/_generated/api/sources/list_sources_api_sources_get.py
seclai/_generated/api/sources/upload_file_to_source_api_sources_source_connection_id_upload_post.py
seclai/_generated/client.py
seclai/_generated/errors.py
seclai/_generated/models/__init__.py
seclai/_generated/models/agent_run_attempt_response.py
seclai/_generated/models/agent_run_list_response.py
seclai/_generated/models/agent_run_request.py
seclai/_generated/models/agent_run_request_metadata_type_0.py
seclai/_generated/models/agent_run_response.py
seclai/_generated/models/agent_run_step_response.py
seclai/_generated/models/agent_run_stream_request.py
seclai/_generated/models/agent_run_stream_request_metadata_type_0.py
seclai/_generated/models/body_upload_file_to_content_api_contents_source_connection_content_version_upload_post.py
seclai-1.0.6.dist-info/METADATA
seclai-1.0.6.dist-info/WHEEL
seclai-1.0.6.dist-info/licenses/LICENSE
seclai-1.0.6.dist-info/RECORD
