Metadata-Version: 2.4
Name: seclai
Version: 1.0.6
Summary: Seclai Python SDK
License-Expression: MIT
License-File: LICENSE
Keywords: Seclai,ai,agent,vector,knowledge base,cloud
Author: Seclai, Inc.
Author-email: support@seclai.com
Requires-Python: >=3.11,<4.0
Classifier: License :: OSI Approved :: MIT License
Classifier: Development Status :: 5 - Production/Stable
Classifier: Intended Audience :: Developers
Classifier: Intended Audience :: Information Technology
Classifier: Intended Audience :: Science/Research
Classifier: Intended Audience :: System Administrators
Classifier: Operating System :: OS Independent
Classifier: Programming Language :: Python :: 3.11
Classifier: Programming Language :: Python :: 3.12
Classifier: Programming Language :: Python :: 3.13
Classifier: Programming Language :: Python :: 3.14
Classifier: Topic :: Database
Classifier: Topic :: Software Development
Classifier: Topic :: Software Development :: Libraries
Classifier: Topic :: Software Development :: Libraries :: Application Frameworks
Classifier: Topic :: Software Development :: Libraries :: Python Modules
Requires-Dist: httpx (>=0.28.1,<0.29.0)
Requires-Dist: pydantic (>=2.12.5,<3.0.0)
Project-URL: Documentation, https://seclai.github.io/seclai-python/1.0.6/
Project-URL: Homepage, https://seclai.com
Project-URL: Repository, https://github.com/seclai/seclai-python
